text_category/__init__.py
text_category/config.py
text_category/data_loader.py
text_category/models.py
text_category/text_category.py
text_category/train_eval.py
text_category/utils.py
text_category-0.0.1.dist-info/LICENSE
text_category-0.0.1.dist-info/METADATA
text_category-0.0.1.dist-info/WHEEL
text_category-0.0.1.dist-info/top_level.txt
text_category-0.0.1.dist-info/RECORD
